Metadata-Version: 1.1
Name: easy-etl
Version: 0.3.2
Summary: A lightweight data cube pipeline for ETL processes in python.
Home-page: https://github.com/kazanz/easy-etl
Author: Zach Kazanski
Author-email: kazanski.zachary@gmail.com
License: UNKNOWN
Platform: UNKNOWN
Classifier: Programming Language :: Python
Classifier: Intended Audience :: Developers
Classifier: Intended Audience :: Science/Research
Classifier: License :: OSI Approved :: MIT License
Classifier: Natural Language :: English
Classifier: Operating System :: OS Independent
Classifier: Development Status :: 4 - Beta
